{"coord":{"lon":-91.5302,"lat":41.6611},"weather":[{"id":800,"main":"Clear","description":"clear sky","icon":"01d"}],"base":"stations","main":{"temp":15.52,"feels_like":15.14,"temp_min":13.32,"temp_max":15.97,"pressure":1015,"humidity":77,"sea_level":1015,"grnd_level":988},"visibility":10000,"wind":{"speed":4.12,"deg":40},"clouds":{"all":0},"dt":1727440508,"sys":{"type":1,"id":4541,"country":"US","sunrise":1727438351,"sunset":1727481274},"timezone":-18000,"id":4862034,"name":"Iowa City","cod":200}
