{"coord":{"lon":-91.5302,"lat":41.6611},"weather":[{"id":800,"main":"Clear","description":"clear sky","icon":"01n"}],"base":"stations","main":{"temp":3.95,"feels_like":2.08,"temp_min":3.36,"temp_max":4.43,"pressure":1007,"humidity":76,"sea_level":1007,"grnd_level":980},"visibility":10000,"wind":{"speed":2.06,"deg":190},"clouds":{"all":0},"dt":1740400632,"sys":{"type":1,"id":4541,"country":"US","sunrise":1740401305,"sunset":1740441030},"timezone":-21600,"id":4862034,"name":"Iowa City","cod":200}
