{"coord":{"lon":-91.5302,"lat":41.6611},"weather":[{"id":800,"main":"Clear","description":"clear sky","icon":"01d"}],"base":"stations","main":{"temp":25.93,"feels_like":26.75,"temp_min":25.55,"temp_max":26.36,"pressure":1008,"humidity":83,"sea_level":1008,"grnd_level":982},"visibility":10000,"wind":{"speed":5.66,"deg":170},"clouds":{"all":0},"dt":1750509419,"sys":{"type":1,"id":4541,"country":"US","sunrise":1750501914,"sunset":1750556639},"timezone":-18000,"id":4862034,"name":"Iowa City","cod":200}
