{"coord":{"lon":-91.5302,"lat":41.6611},"weather":[{"id":801,"main":"Clouds","description":"few clouds","icon":"02n"}],"base":"stations","main":{"temp":1.08,"feels_like":-3.04,"temp_min":0.55,"temp_max":1.23,"pressure":1014,"humidity":80,"sea_level":1014,"grnd_level":987},"visibility":10000,"wind":{"speed":4.12,"deg":270},"clouds":{"all":20},"dt":1740659812,"sys":{"type":1,"id":4541,"country":"US","sunrise":1740660229,"sunset":1740700446},"timezone":-21600,"id":4862034,"name":"Iowa City","cod":200}
